genno/__init__.py
genno/caching.py
genno/computations.py
genno/config.py
genno/operator.py
genno/py.typed
genno/types.py
genno/util.py
genno/compat/__init__.py
genno/compat/_test.py
genno/compat/dask.py
genno/compat/graphviz.py
genno/compat/pandas.py
genno/compat/pint.py
genno/compat/xarray.py
genno/compat/plotnine/__init__.py
genno/compat/plotnine/plot.py
genno/compat/pyam/__init__.py
genno/compat/pyam/operator.py
genno/compat/pyam/util.py
genno/compat/sdmx/__init__.py
genno/compat/sdmx/operator.py
genno/compat/sdmx/util.py
genno/compat/sphinx/__init__.py
genno/compat/sphinx/autodoc_operator.py
genno/compat/sphinx/rewrite_refs.py
genno/core/__init__.py
genno/core/attrseries.py
genno/core/base.py
genno/core/computer.py
genno/core/describe.py
genno/core/eval.py
genno/core/exceptions.py
genno/core/graph.py
genno/core/key.py
genno/core/operator.py
genno/core/quantity.py
genno/core/sparsedataarray.py
genno/testing/__init__.py
genno/testing/jupyter.py
genno/tests/__init__.py
genno/tests/test_caching.py
genno/tests/test_config.py
genno/tests/test_core.py
genno/tests/test_operator.py
genno/tests/test_testing.py
genno/tests/test_util.py
genno/tests/compat/__init__.py
genno/tests/compat/test_compat.py
genno/tests/compat/test_plotnine.py
genno/tests/compat/test_pyam.py
genno/tests/compat/test_sdmx.py
genno/tests/core/__init__.py
genno/tests/core/test_attrseries.py
genno/tests/core/test_computer.py
genno/tests/core/test_describe.py
genno/tests/core/test_exceptions.py
genno/tests/core/test_graph.py
genno/tests/core/test_key.py
genno/tests/core/test_operator.py
genno/tests/core/test_quantity.py
genno/tests/core/test_sparsedataarray.py
genno/tests/data/22_289-structure.xml
genno/tests/data/22_289.xml
genno/tests/data/config-0.json
genno/tests/data/config-0.yaml
genno/tests/data/config-aggregate0.yaml
genno/tests/data/config-aggregate1.yaml
genno/tests/data/config-aggregate2.yaml
genno/tests/data/config-combine.yaml
genno/tests/data/config-general0.yaml
genno-1.29.0.dist-info/METADATA
genno-1.29.0.dist-info/WHEEL
genno-1.29.0.dist-info/licenses/LICENSE
genno-1.29.0.dist-info/RECORD
