Metadata-Version: 2.4
Name: genno
Version: 1.29.0
Summary: Efficient, transparent calculation on N-D data
Project-URL: homepage, https://github.com/khaeru/genno
Project-URL: repository, https://github.com/khaeru/genno
Project-URL: documentation, https://genno.rtfd.io/en/stable/
Author: genno contributors
Maintainer-email: Paul Natsuo Kishimoto <mail@paul.kishimoto.name>
License-File: LICENSE
Classifier: Intended Audience :: Developers
Classifier: Intended Audience :: Science/Research
Classifier: Operating System :: OS Independent
Classifier: Programming Language :: Python
Classifier: Programming Language :: Python :: 3
Classifier: Programming Language :: Python :: 3.10
Classifier: Programming Language :: Python :: 3.11
Classifier: Programming Language :: Python :: 3.12
Classifier: Programming Language :: Python :: 3.13
Classifier: Programming Language :: Python :: 3.14
Classifier: Topic :: Scientific/Engineering
Classifier: Topic :: Scientific/Engineering :: Information Analysis
Requires-Python: >=3.10
Requires-Dist: dask[array]>=2.14
Requires-Dist: fastparquet; python_version >= '3.14'
Requires-Dist: pandas>=1.0
Requires-Dist: pandas[parquet]; python_version < '3.14'
Requires-Dist: pint
Requires-Dist: platformdirs
Requires-Dist: pyyaml
Requires-Dist: xarray!=2022.6.0,>=0.17
Provides-Extra: compat
Requires-Dist: plotnine; extra == 'compat'
Requires-Dist: pyam-iamc; extra == 'compat'
Requires-Dist: sdmx1; extra == 'compat'
Provides-Extra: docs
Requires-Dist: furo; extra == 'docs'
Requires-Dist: ipython; extra == 'docs'
Requires-Dist: pickleshare; extra == 'docs'
Provides-Extra: graphviz
Requires-Dist: graphviz; extra == 'graphviz'
Provides-Extra: plotnine
Requires-Dist: plotnine; extra == 'plotnine'
Provides-Extra: pyam
Requires-Dist: pyam-iamc; extra == 'pyam'
Provides-Extra: sdmx
Requires-Dist: sdmx1; extra == 'sdmx'
Provides-Extra: sparse
Requires-Dist: numba>=0.54; extra == 'sparse'
Requires-Dist: sparse>=0.12; extra == 'sparse'
Provides-Extra: tests
Requires-Dist: bottleneck; extra == 'tests'
Requires-Dist: graphviz; extra == 'tests'
Requires-Dist: jupyter; extra == 'tests'
Requires-Dist: nbclient; extra == 'tests'
Requires-Dist: plotnine; extra == 'tests'
Requires-Dist: pyam-iamc; extra == 'tests'
Requires-Dist: pytest; extra == 'tests'
Requires-Dist: pytest-cov; extra == 'tests'
Requires-Dist: pytest-rerunfailures; extra == 'tests'
Requires-Dist: pytest-xdist; extra == 'tests'
Requires-Dist: sdmx1; extra == 'tests'
